{
    "_config_name": "node.type.stanford_event",
    "type": "stanford_event",
    "name": "Stanford Event",
    "base": "node_content",
    "module": "node",
    "description": "An event pulled in from <a href=\"https://events-legacy.stanford.edu\">events-legacy.stanford.edu</a>.",
    "help": "",
    "has_title": true,
    "title_label": "Title",
    "modified": true,
    "disabled": false,
    "orig_type": "stanford_event",
    "settings": {
        "status_default": 1,
        "sticky_enabled": true,
        "sticky_default": false,
        "promote_enabled": true,
        "promote_default": false,
        "revision_enabled": true,
        "revision_default": true,
        "node_preview": "1",
        "node_submitted": 0,
        "node_user_picture": true,
        "language": null,
        "menu_default": false,
        "menu_options": [],
        "menu_parent": "main-menu:0",
        "scheduling_enabled": true,
        "node_submitted_format": "[node:created:medium] by [node:author]",
        "hidden_path": "0",
        "node_permissions": true,
        "comment_default": 1
    },
    "node_preview": 1
}
